{
  "dexed": 1697,
  "sf2": 1926,
  "sfz": 1106,
  "m8": 1784,
  "minijv": 1794,
  "obxd": 1272,
  "cloudseed": 1397,
  "midiverb": 138,
  "tapescam": 1384,
  "psxverb": 1176,
  "tapedelay": 2058,
  "junologue-chorus": 1198,
  "sidcontrol": 1080,
  "braids": 1248,
  "hera": 1202,
  "surge": 1228,
  "moog": 1581,
  "webstream": 1886,
  "nam": 1184,
  "ducker": 1289,
  "radiogarden": 1436,
  "airplay": 1868,
  "streamrtsp": 645,
  "clap": 1133,
  "gate": 1627,
  "control": 1756,
  "chiptune": 1486,
  "keydetect": 1502,
  "vocoder": 1145,
  "osirus": 1885,
  "superarp": 1380,
  "eucalypso": 1200,
  "granny": 1638,
  "freak": 916,
  "mrdrums": 1169,
  "rex": 1564,
  "hush1": 1412,
  "nusaw": 1134,
  "usefulity": 1258,
  "samplerobot": 825,
  "waveform-editor": 1868,
  "stretch": 1336,
  "stems": 1184,
  "plaits": 1117,
  "granular": 1294,
  "superboom": 943,
  "performance-fx": 909,
  "dj": 831,
  "slicer": 643,
  "verglas": 730,
  "tuner": 717,
  "dragonfly-hall": 780,
  "punchfx": 910,
  "structor": 945,
  "weird-dreams": 1063,
  "dissolver": 853,
  "spectra": 947,
  "essaim": 750,
  "chowtape": 694,
  "wurl": 640,
  "denis": 632,
  "genera": 683,
  "euclidrum": 313,
  "branchage": 675,
  "twinsampler": 447,
  "impressive-chords": 283,
  "303": 142,
  "tb3po": 147
}
