{
  "dexed": 1779,
  "sf2": 1963,
  "sfz": 1165,
  "m8": 1823,
  "minijv": 1853,
  "obxd": 1314,
  "cloudseed": 1443,
  "midiverb": 206,
  "tapescam": 1426,
  "psxverb": 1218,
  "tapedelay": 2098,
  "junologue-chorus": 1240,
  "sidcontrol": 1113,
  "braids": 1293,
  "hera": 1245,
  "surge": 1273,
  "moog": 1618,
  "webstream": 1965,
  "nam": 1216,
  "ducker": 1331,
  "radiogarden": 1482,
  "airplay": 1937,
  "streamrtsp": 686,
  "clap": 1172,
  "gate": 1664,
  "control": 1794,
  "chiptune": 1526,
  "keydetect": 1539,
  "vocoder": 1181,
  "osirus": 1941,
  "superarp": 1419,
  "eucalypso": 1233,
  "granny": 1684,
  "freak": 964,
  "mrdrums": 1209,
  "rex": 1615,
  "hush1": 1452,
  "nusaw": 1171,
  "usefulity": 1292,
  "samplerobot": 867,
  "waveform-editor": 1953,
  "stretch": 1385,
  "stems": 1231,
  "plaits": 1173,
  "granular": 1339,
  "superboom": 982,
  "performance-fx": 953,
  "dj": 870,
  "slicer": 692,
  "verglas": 772,
  "guitar-tuner": 62,
  "tuner": 754,
  "dragonfly-hall": 817,
  "punchfx": 955,
  "structor": 990,
  "weird-dreams": 1107,
  "dissolver": 895,
  "spectra": 996,
  "essaim": 798,
  "chowtape": 739,
  "wurl": 679,
  "denis": 682,
  "genera": 739,
  "euclidrum": 371,
  "branchage": 726,
  "twinsampler": 521,
  "impressive-chords": 412,
  "ai-manual": 56,
  "ai-assistant": 57,
  "303": 237,
  "tb3po": 288
}
