{
  "dexed": 1894,
  "sf2": 2034,
  "sfz": 1321,
  "m8": 1892,
  "minijv": 1950,
  "obxd": 1440,
  "cloudseed": 1527,
  "midiverb": 305,
  "tapescam": 1509,
  "psxverb": 1282,
  "tapedelay": 2183,
  "junologue-chorus": 1308,
  "sidcontrol": 1169,
  "braids": 1385,
  "hera": 1317,
  "surge": 1354,
  "moog": 1682,
  "webstream": 2058,
  "nam": 1278,
  "ducker": 1410,
  "radiogarden": 1560,
  "airplay": 2039,
  "streamrtsp": 753,
  "clap": 1241,
  "gate": 1725,
  "control": 1864,
  "chiptune": 1604,
  "keydetect": 1601,
  "vocoder": 1248,
  "osirus": 2036,
  "superarp": 1492,
  "eucalypso": 1297,
  "granny": 1770,
  "freak": 1049,
  "mrdrums": 1280,
  "rex": 1692,
  "hush1": 1527,
  "nusaw": 1240,
  "usefulity": 1359,
  "samplerobot": 936,
  "waveform-editor": 2064,
  "stretch": 1461,
  "stems": 1310,
  "plaits": 1266,
  "granular": 1432,
  "superboom": 1054,
  "performance-fx": 1031,
  "dj": 932,
  "slicer": 771,
  "verglas": 848,
  "guitar-tuner": 170,
  "tuner": 817,
  "dragonfly-hall": 891,
  "punchfx": 1040,
  "structor": 1071,
  "weird-dreams": 1199,
  "dissolver": 997,
  "spectra": 1090,
  "essaim": 900,
  "chowtape": 829,
  "wurl": 775,
  "denis": 781,
  "genera": 835,
  "euclidrum": 475,
  "branchage": 819,
  "twinsampler": 626,
  "impressive-chords": 560,
  "ai-manual": 159,
  "ai-assistant": 166,
  "303": 372,
  "tb3po": 426,
  "breakbeat": 180,
  "signal": 47,
  "krautdrums": 47,
  "forge": 50
}
