{
  "dexed": 2317,
  "sf2": 2338,
  "sfz": 1839,
  "m8": 2186,
  "minijv": 2323,
  "obxd": 1951,
  "cloudseed": 1866,
  "midiverb": 632,
  "tapescam": 1841,
  "psxverb": 1596,
  "mverb": 391,
  "tapedelay": 2537,
  "junologue-chorus": 1640,
  "sidcontrol": 1442,
  "braids": 1748,
  "hera": 1643,
  "surge": 1706,
  "moog": 1979,
  "webstream": 2444,
  "nam": 1639,
  "ducker": 1730,
  "radiogarden": 1900,
  "airplay": 2406,
  "streamrtsp": 1031,
  "clap": 1758,
  "gate": 2008,
  "control": 2171,
  "chiptune": 1934,
  "keydetect": 1905,
  "vocoder": 1545,
  "osirus": 2407,
  "superarp": 1825,
  "eucalypso": 1597,
  "granny": 2099,
  "freak": 1360,
  "mrdrums": 1579,
  "rex": 1992,
  "hush1": 1848,
  "nusaw": 1538,
  "usefulity": 1652,
  "samplerobot": 1246,
  "waveform-editor": 2414,
  "stretch": 1773,
  "stems": 1634,
  "plaits": 1633,
  "granular": 1779,
  "superboom": 1361,
  "performance-fx": 1352,
  "dj": 1223,
  "slicer": 1084,
  "verglas": 1159,
  "guitar-tuner": 509,
  "tuner": 1100,
  "dragonfly-hall": 1192,
  "punchfx": 1361,
  "structor": 1366,
  "weird-dreams": 1658,
  "dissolver": 2077,
  "spectra": 1528,
  "essaim": 1337,
  "chowtape": 1162,
  "ambiotica": 414,
  "filter": 25,
  "wurl": 1234,
  "denis": 1226,
  "genera": 1289,
  "euclidrum": 1518,
  "branchage": 1134,
  "twinsampler": 945,
  "impressive-chords": 959,
  "midi-player": 411,
  "ai-manual": 479,
  "ai-assistant": 491,
  "303": 807,
  "tb3po": 791,
  "breakbeat": 706,
  "signal": 460,
  "krautdrums": 477,
  "forge": 486,
  "davebox": 530,
  "chorddex": 484,
  "mrsample": 416,
  "dronage-tool": 319,
  "chordism": 158,
  "juno_control": 80,
  "helm": 129
}
