{
  "dexed": 2832,
  "sf2": 2719,
  "sfz": 2337,
  "m8": 2555,
  "minijv": 3035,
  "obxd": 2794,
  "cloudseed": 2288,
  "ottx": 531,
  "midiverb": 1046,
  "tapescam": 2253,
  "psxverb": 1979,
  "mverb": 845,
  "tapedelay": 2960,
  "junologue-chorus": 2022,
  "sidcontrol": 1781,
  "braids": 2207,
  "hera": 2052,
  "surge": 2408,
  "moog": 2358,
  "webstream": 3252,
  "nam": 2223,
  "ducker": 2150,
  "pushnpull": 378,
  "radiogarden": 2542,
  "airplay": 2850,
  "streamrtsp": 1387,
  "clap": 2288,
  "gate": 2364,
  "control": 2962,
  "chiptune": 2335,
  "keydetect": 2287,
  "vocoder": 1923,
  "osirus": 3093,
  "superarp": 2241,
  "eucalypso": 1977,
  "granny": 2506,
  "freak": 1740,
  "mrdrums": 2193,
  "rex": 2370,
  "hush1": 2252,
  "nusaw": 1914,
  "usefulity": 2020,
  "samplerobot": 1620,
  "waveform-editor": 2860,
  "stretch": 2192,
  "stems": 2039,
  "plaits": 2076,
  "granular": 2186,
  "superboom": 1749,
  "performance-fx": 1765,
  "dj": 1584,
  "slicer": 1476,
  "verglas": 1545,
  "guitar-tuner": 923,
  "tuner": 1461,
  "dragonfly-hall": 1579,
  "punchfx": 1775,
  "structor": 1756,
  "weird-dreams": 2147,
  "dissolver": 2808,
  "spectra": 1983,
  "essaim": 1813,
  "chowtape": 1573,
  "ambiotica": 1376,
  "filter": 656,
  "wurl": 1726,
  "denis": 1697,
  "genera": 1791,
  "euclidrum": 3009,
  "branchage": 1522,
  "twinsampler": 1682,
  "impressive-chords": 1444,
  "midi-player": 1001,
  "ai-manual": 887,
  "ai-assistant": 905,
  "303": 1323,
  "tb3po": 1462,
  "breakbeat": 1352,
  "po32-drum": 727,
  "signal": 907,
  "krautdrums": 935,
  "forge": 1133,
  "davebox": 1353,
  "chorddex": 1200,
  "mrsample": 867,
  "dronage-tool": 1106,
  "chordism": 798,
  "juno_control": 581,
  "helm": 903,
  "fork": 451,
  "aphex": 479,
  "war_bells": 485,
  "movy": 378,
  "magneto": 261,
  "fizzik": 276,
  "palette": 279,
  "smack": 233,
  "smack-in": 255,
  "oversmack": 178,
  "mark": 202,
  "belt": 139,
  "belt-in": 169,
  "mono": 129,
  "mono-voice": 94,
  "noisemaker": 25
}
