{
  "dexed": 2806,
  "sf2": 2696,
  "sfz": 2315,
  "m8": 2533,
  "minijv": 3003,
  "obxd": 2763,
  "cloudseed": 2265,
  "ottx": 506,
  "midiverb": 1022,
  "tapescam": 2230,
  "psxverb": 1956,
  "mverb": 822,
  "tapedelay": 2935,
  "junologue-chorus": 2000,
  "sidcontrol": 1760,
  "braids": 2181,
  "hera": 2028,
  "surge": 2376,
  "moog": 2337,
  "webstream": 3222,
  "nam": 2200,
  "ducker": 2127,
  "pushnpull": 351,
  "radiogarden": 2501,
  "airplay": 2825,
  "streamrtsp": 1366,
  "clap": 2258,
  "gate": 2343,
  "control": 2906,
  "chiptune": 2311,
  "keydetect": 2264,
  "vocoder": 1899,
  "osirus": 3058,
  "superarp": 2216,
  "eucalypso": 1953,
  "granny": 2482,
  "freak": 1716,
  "mrdrums": 2161,
  "rex": 2349,
  "hush1": 2229,
  "nusaw": 1891,
  "usefulity": 1998,
  "samplerobot": 1598,
  "waveform-editor": 2838,
  "stretch": 2171,
  "stems": 2017,
  "plaits": 2052,
  "granular": 2162,
  "superboom": 1724,
  "performance-fx": 1742,
  "dj": 1561,
  "slicer": 1454,
  "verglas": 1523,
  "guitar-tuner": 900,
  "tuner": 1441,
  "dragonfly-hall": 1556,
  "punchfx": 1753,
  "structor": 1733,
  "weird-dreams": 2124,
  "dissolver": 2777,
  "spectra": 1961,
  "essaim": 1790,
  "chowtape": 1550,
  "ambiotica": 1323,
  "filter": 632,
  "wurl": 1702,
  "denis": 1675,
  "genera": 1765,
  "euclidrum": 2970,
  "branchage": 1497,
  "twinsampler": 1654,
  "impressive-chords": 1418,
  "midi-player": 970,
  "ai-manual": 863,
  "ai-assistant": 880,
  "303": 1294,
  "tb3po": 1433,
  "breakbeat": 1325,
  "po32-drum": 700,
  "signal": 885,
  "krautdrums": 911,
  "forge": 1074,
  "davebox": 1290,
  "chorddex": 1169,
  "mrsample": 842,
  "dronage-tool": 1068,
  "chordism": 773,
  "juno_control": 558,
  "helm": 878,
  "fork": 424,
  "aphex": 449,
  "war_bells": 457,
  "movy": 316,
  "magneto": 230,
  "fizzik": 245,
  "palette": 247,
  "smack": 180,
  "smack-in": 206,
  "oversmack": 133,
  "mark": 136,
  "belt": 108,
  "belt-in": 119,
  "mono": 38,
  "mono-voice": 21
}
