{
  "dexed": 1931,
  "sf2": 2059,
  "sfz": 1360,
  "m8": 1914,
  "minijv": 1982,
  "obxd": 1512,
  "cloudseed": 1556,
  "midiverb": 333,
  "tapescam": 1533,
  "psxverb": 1308,
  "tapedelay": 2210,
  "junologue-chorus": 1333,
  "sidcontrol": 1190,
  "braids": 1419,
  "hera": 1344,
  "surge": 1381,
  "moog": 1709,
  "webstream": 2088,
  "nam": 1301,
  "ducker": 1437,
  "radiogarden": 1591,
  "airplay": 2074,
  "streamrtsp": 776,
  "clap": 1320,
  "gate": 1749,
  "control": 1889,
  "chiptune": 1631,
  "keydetect": 1629,
  "vocoder": 1274,
  "osirus": 2065,
  "superarp": 1518,
  "eucalypso": 1321,
  "granny": 1795,
  "freak": 1076,
  "mrdrums": 1306,
  "rex": 1718,
  "hush1": 1553,
  "nusaw": 1267,
  "usefulity": 1383,
  "samplerobot": 963,
  "waveform-editor": 2096,
  "stretch": 1486,
  "stems": 1339,
  "plaits": 1296,
  "granular": 1463,
  "superboom": 1081,
  "performance-fx": 1058,
  "dj": 956,
  "slicer": 802,
  "verglas": 873,
  "guitar-tuner": 199,
  "tuner": 838,
  "dragonfly-hall": 915,
  "punchfx": 1070,
  "structor": 1097,
  "weird-dreams": 1284,
  "dissolver": 1161,
  "spectra": 1168,
  "essaim": 975,
  "chowtape": 858,
  "wurl": 850,
  "denis": 860,
  "genera": 913,
  "euclidrum": 618,
  "branchage": 849,
  "twinsampler": 657,
  "impressive-chords": 598,
  "midi-player": 32,
  "ai-manual": 185,
  "ai-assistant": 195,
  "303": 411,
  "tb3po": 459,
  "breakbeat": 251,
  "signal": 110,
  "krautdrums": 112,
  "forge": 121,
  "davebox": 105,
  "mrsample": 10
}
