{
  "dexed": 1924,
  "sf2": 2054,
  "sfz": 1353,
  "m8": 1911,
  "minijv": 1977,
  "obxd": 1501,
  "cloudseed": 1551,
  "midiverb": 327,
  "tapescam": 1528,
  "psxverb": 1303,
  "tapedelay": 2204,
  "junologue-chorus": 1327,
  "sidcontrol": 1187,
  "braids": 1412,
  "hera": 1338,
  "surge": 1375,
  "moog": 1704,
  "webstream": 2082,
  "nam": 1297,
  "ducker": 1431,
  "radiogarden": 1586,
  "airplay": 2067,
  "streamrtsp": 771,
  "clap": 1299,
  "gate": 1743,
  "control": 1885,
  "chiptune": 1626,
  "keydetect": 1622,
  "vocoder": 1268,
  "osirus": 2060,
  "superarp": 1513,
  "eucalypso": 1316,
  "granny": 1791,
  "freak": 1070,
  "mrdrums": 1300,
  "rex": 1713,
  "hush1": 1547,
  "nusaw": 1262,
  "usefulity": 1376,
  "samplerobot": 957,
  "waveform-editor": 2089,
  "stretch": 1481,
  "stems": 1333,
  "plaits": 1290,
  "granular": 1456,
  "superboom": 1074,
  "performance-fx": 1054,
  "dj": 951,
  "slicer": 795,
  "verglas": 868,
  "guitar-tuner": 194,
  "tuner": 835,
  "dragonfly-hall": 911,
  "punchfx": 1064,
  "structor": 1090,
  "weird-dreams": 1271,
  "dissolver": 1141,
  "spectra": 1156,
  "essaim": 964,
  "chowtape": 852,
  "wurl": 838,
  "denis": 849,
  "genera": 900,
  "euclidrum": 598,
  "branchage": 841,
  "twinsampler": 651,
  "impressive-chords": 589,
  "midi-player": 19,
  "ai-manual": 179,
  "ai-assistant": 189,
  "303": 403,
  "tb3po": 452,
  "breakbeat": 234,
  "signal": 100,
  "krautdrums": 102,
  "forge": 112,
  "davebox": 90
}
