{
  "dexed": 2002,
  "sf2": 2105,
  "sfz": 1500,
  "m8": 1962,
  "minijv": 2041,
  "obxd": 1607,
  "cloudseed": 1613,
  "midiverb": 388,
  "tapescam": 1585,
  "psxverb": 1355,
  "mverb": 104,
  "tapedelay": 2264,
  "junologue-chorus": 1382,
  "sidcontrol": 1232,
  "braids": 1473,
  "hera": 1390,
  "surge": 1435,
  "moog": 1756,
  "webstream": 2147,
  "nam": 1345,
  "ducker": 1486,
  "radiogarden": 1641,
  "airplay": 2133,
  "streamrtsp": 815,
  "clap": 1448,
  "gate": 1792,
  "control": 1935,
  "chiptune": 1676,
  "keydetect": 1675,
  "vocoder": 1318,
  "osirus": 2122,
  "superarp": 1566,
  "eucalypso": 1366,
  "granny": 1842,
  "freak": 1121,
  "mrdrums": 1353,
  "rex": 1768,
  "hush1": 1598,
  "nusaw": 1311,
  "usefulity": 1427,
  "samplerobot": 1008,
  "waveform-editor": 2154,
  "stretch": 1534,
  "stems": 1387,
  "plaits": 1355,
  "granular": 1519,
  "superboom": 1130,
  "performance-fx": 1103,
  "dj": 998,
  "slicer": 850,
  "verglas": 919,
  "guitar-tuner": 264,
  "tuner": 878,
  "dragonfly-hall": 962,
  "punchfx": 1120,
  "structor": 1142,
  "weird-dreams": 1367,
  "dissolver": 1402,
  "spectra": 1246,
  "essaim": 1055,
  "chowtape": 909,
  "wurl": 933,
  "denis": 941,
  "genera": 995,
  "euclidrum": 830,
  "branchage": 895,
  "twinsampler": 710,
  "impressive-chords": 667,
  "midi-player": 139,
  "ai-manual": 245,
  "ai-assistant": 254,
  "303": 479,
  "tb3po": 524,
  "breakbeat": 365,
  "signal": 193,
  "krautdrums": 194,
  "forge": 205,
  "davebox": 207,
  "chorddex": 29,
  "mrsample": 138
}
