{
  "dexed": 1348,
  "sf2": 1780,
  "sfz": 947,
  "m8": 1640,
  "minijv": 1588,
  "obxd": 1110,
  "cloudseed": 1229,
  "tapescam": 1216,
  "psxverb": 1033,
  "tapedelay": 1896,
  "junologue-chorus": 1040,
  "sidcontrol": 947,
  "braids": 1080,
  "hera": 1049,
  "surge": 1061,
  "moog": 1430,
  "webstream": 1686,
  "nam": 1036,
  "ducker": 1129,
  "radiogarden": 1276,
  "airplay": 1574,
  "streamrtsp": 509,
  "clap": 994,
  "gate": 1486,
  "control": 1599,
  "chiptune": 1337,
  "keydetect": 1362,
  "vocoder": 1002,
  "osirus": 1707,
  "superarp": 1229,
  "eucalypso": 1054,
  "granny": 1470,
  "freak": 744,
  "mrdrums": 1000,
  "rex": 1401,
  "hush1": 1263,
  "nusaw": 992,
  "usefulity": 1116,
  "samplerobot": 685,
  "waveform-editor": 1591,
  "stretch": 1167,
  "stems": 1012,
  "plaits": 938,
  "granular": 1126,
  "superboom": 799,
  "performance-fx": 752,
  "dj": 694,
  "slicer": 484,
  "verglas": 586,
  "tuner": 578,
  "dragonfly-hall": 632,
  "punchfx": 753,
  "structor": 788,
  "weird-dreams": 888,
  "dissolver": 698,
  "spectra": 780,
  "essaim": 585,
  "chowtape": 525,
  "wurl": 469,
  "denis": 472,
  "genera": 470,
  "euclidrum": 98,
  "branchage": 483,
  "twinsampler": 126
}
