{
  "dexed": 2162,
  "sf2": 2225,
  "sfz": 1685,
  "m8": 2078,
  "minijv": 2192,
  "obxd": 1786,
  "cloudseed": 1744,
  "midiverb": 514,
  "tapescam": 1706,
  "psxverb": 1477,
  "mverb": 264,
  "tapedelay": 2396,
  "junologue-chorus": 1509,
  "sidcontrol": 1340,
  "braids": 1617,
  "hera": 1521,
  "surge": 1573,
  "moog": 1872,
  "webstream": 2307,
  "nam": 1459,
  "ducker": 1610,
  "radiogarden": 1774,
  "airplay": 2272,
  "streamrtsp": 932,
  "clap": 1613,
  "gate": 1903,
  "control": 2056,
  "chiptune": 1803,
  "keydetect": 1795,
  "vocoder": 1433,
  "osirus": 2275,
  "superarp": 1699,
  "eucalypso": 1490,
  "granny": 1981,
  "freak": 1249,
  "mrdrums": 1474,
  "rex": 1891,
  "hush1": 1726,
  "nusaw": 1428,
  "usefulity": 1544,
  "samplerobot": 1130,
  "waveform-editor": 2287,
  "stretch": 1656,
  "stems": 1516,
  "plaits": 1506,
  "granular": 1653,
  "superboom": 1248,
  "performance-fx": 1233,
  "dj": 1115,
  "slicer": 969,
  "verglas": 1042,
  "guitar-tuner": 391,
  "tuner": 992,
  "dragonfly-hall": 1083,
  "punchfx": 1250,
  "structor": 1262,
  "weird-dreams": 1518,
  "dissolver": 1745,
  "spectra": 1400,
  "essaim": 1203,
  "chowtape": 1042,
  "ambiotica": 182,
  "wurl": 1088,
  "denis": 1093,
  "genera": 1146,
  "euclidrum": 1141,
  "branchage": 1027,
  "twinsampler": 833,
  "impressive-chords": 818,
  "midi-player": 291,
  "ai-manual": 370,
  "ai-assistant": 378,
  "303": 649,
  "tb3po": 667,
  "breakbeat": 542,
  "signal": 335,
  "krautdrums": 342,
  "forge": 353,
  "davebox": 352,
  "chorddex": 254,
  "mrsample": 294
}
