{
  "dexed": 2602,
  "sf2": 2534,
  "sfz": 2110,
  "m8": 2373,
  "minijv": 2648,
  "obxd": 2351,
  "cloudseed": 2082,
  "ottx": 262,
  "midiverb": 848,
  "tapescam": 2056,
  "psxverb": 1795,
  "mverb": 632,
  "tapedelay": 2760,
  "junologue-chorus": 1840,
  "sidcontrol": 1619,
  "braids": 1989,
  "hera": 1859,
  "surge": 2029,
  "moog": 2182,
  "webstream": 2936,
  "nam": 1982,
  "ducker": 1954,
  "radiogarden": 2134,
  "airplay": 2644,
  "streamrtsp": 1217,
  "clap": 2048,
  "gate": 2196,
  "control": 2575,
  "chiptune": 2148,
  "keydetect": 2104,
  "vocoder": 1745,
  "osirus": 2678,
  "superarp": 2037,
  "eucalypso": 1795,
  "granny": 2305,
  "freak": 1548,
  "mrdrums": 1806,
  "rex": 2188,
  "hush1": 2063,
  "nusaw": 1733,
  "usefulity": 1847,
  "samplerobot": 1442,
  "waveform-editor": 2651,
  "stretch": 1993,
  "stems": 1841,
  "plaits": 1859,
  "granular": 1986,
  "superboom": 1559,
  "performance-fx": 1566,
  "dj": 1410,
  "slicer": 1285,
  "verglas": 1357,
  "guitar-tuner": 724,
  "tuner": 1287,
  "dragonfly-hall": 1391,
  "punchfx": 1569,
  "structor": 1565,
  "weird-dreams": 1919,
  "dissolver": 2500,
  "spectra": 1768,
  "essaim": 1589,
  "chowtape": 1376,
  "ambiotica": 820,
  "filter": 406,
  "wurl": 1503,
  "denis": 1480,
  "genera": 1555,
  "euclidrum": 2393,
  "branchage": 1330,
  "twinsampler": 1403,
  "impressive-chords": 1206,
  "midi-player": 641,
  "ai-manual": 689,
  "ai-assistant": 703,
  "303": 1085,
  "tb3po": 1169,
  "breakbeat": 1093,
  "po32-drum": 451,
  "signal": 691,
  "krautdrums": 714,
  "forge": 724,
  "davebox": 905,
  "chorddex": 812,
  "mrsample": 652,
  "dronage-tool": 685,
  "chordism": 538,
  "juno_control": 362,
  "helm": 630,
  "fork": 200,
  "aphex": 125,
  "war_bells": 92
}
