{
  "dexed": 2816,
  "sf2": 2703,
  "sfz": 2322,
  "m8": 2541,
  "minijv": 3013,
  "obxd": 2773,
  "cloudseed": 2272,
  "ottx": 514,
  "midiverb": 1029,
  "tapescam": 2237,
  "psxverb": 1963,
  "mverb": 829,
  "tapedelay": 2944,
  "junologue-chorus": 2007,
  "sidcontrol": 1767,
  "braids": 2192,
  "hera": 2036,
  "surge": 2386,
  "moog": 2344,
  "webstream": 3231,
  "nam": 2207,
  "ducker": 2135,
  "pushnpull": 360,
  "radiogarden": 2516,
  "airplay": 2833,
  "streamrtsp": 1373,
  "clap": 2269,
  "gate": 2350,
  "control": 2926,
  "chiptune": 2320,
  "keydetect": 2271,
  "vocoder": 1907,
  "osirus": 3067,
  "superarp": 2224,
  "eucalypso": 1961,
  "granny": 2490,
  "freak": 1723,
  "mrdrums": 2170,
  "rex": 2356,
  "hush1": 2237,
  "nusaw": 1899,
  "usefulity": 2005,
  "samplerobot": 1605,
  "waveform-editor": 2845,
  "stretch": 2178,
  "stems": 2026,
  "plaits": 2060,
  "granular": 2170,
  "superboom": 1731,
  "performance-fx": 1749,
  "dj": 1568,
  "slicer": 1461,
  "verglas": 1530,
  "guitar-tuner": 908,
  "tuner": 1448,
  "dragonfly-hall": 1563,
  "punchfx": 1761,
  "structor": 1740,
  "weird-dreams": 2132,
  "dissolver": 2787,
  "spectra": 1968,
  "essaim": 1797,
  "chowtape": 1557,
  "ambiotica": 1341,
  "filter": 639,
  "wurl": 1711,
  "denis": 1682,
  "genera": 1773,
  "euclidrum": 2983,
  "branchage": 1506,
  "twinsampler": 1662,
  "impressive-chords": 1426,
  "midi-player": 980,
  "ai-manual": 870,
  "ai-assistant": 887,
  "303": 1302,
  "tb3po": 1441,
  "breakbeat": 1333,
  "po32-drum": 708,
  "signal": 892,
  "krautdrums": 919,
  "forge": 1086,
  "davebox": 1300,
  "chorddex": 1181,
  "mrsample": 849,
  "dronage-tool": 1081,
  "chordism": 782,
  "juno_control": 565,
  "helm": 886,
  "fork": 434,
  "aphex": 459,
  "war_bells": 466,
  "movy": 327,
  "magneto": 241,
  "fizzik": 256,
  "palette": 258,
  "smack": 180,
  "smack-in": 224,
  "oversmack": 152,
  "mark": 162,
  "belt": 108,
  "belt-in": 139,
  "mono": 69,
  "mono-voice": 52
}
