{
  "dexed": 2365,
  "sf2": 2372,
  "sfz": 1897,
  "m8": 2219,
  "minijv": 2361,
  "obxd": 2004,
  "cloudseed": 1902,
  "midiverb": 671,
  "tapescam": 1877,
  "psxverb": 1635,
  "mverb": 435,
  "tapedelay": 2576,
  "junologue-chorus": 1675,
  "sidcontrol": 1475,
  "braids": 1791,
  "hera": 1681,
  "surge": 1749,
  "moog": 2014,
  "webstream": 2597,
  "nam": 1715,
  "ducker": 1769,
  "radiogarden": 1943,
  "airplay": 2450,
  "streamrtsp": 1064,
  "clap": 1816,
  "gate": 2041,
  "control": 2281,
  "chiptune": 1968,
  "keydetect": 1939,
  "vocoder": 1579,
  "osirus": 2446,
  "superarp": 1862,
  "eucalypso": 1631,
  "granny": 2132,
  "freak": 1394,
  "mrdrums": 1612,
  "rex": 2026,
  "hush1": 1886,
  "nusaw": 1572,
  "usefulity": 1687,
  "samplerobot": 1282,
  "waveform-editor": 2456,
  "stretch": 1807,
  "stems": 1671,
  "plaits": 1673,
  "granular": 1813,
  "superboom": 1398,
  "performance-fx": 1390,
  "dj": 1254,
  "slicer": 1118,
  "verglas": 1197,
  "guitar-tuner": 551,
  "tuner": 1136,
  "dragonfly-hall": 1227,
  "punchfx": 1396,
  "structor": 1404,
  "weird-dreams": 1708,
  "dissolver": 2177,
  "spectra": 1576,
  "essaim": 1388,
  "chowtape": 1198,
  "ambiotica": 476,
  "filter": 127,
  "wurl": 1283,
  "denis": 1280,
  "genera": 1341,
  "euclidrum": 1683,
  "branchage": 1169,
  "twinsampler": 1000,
  "impressive-chords": 1004,
  "midi-player": 456,
  "ai-manual": 519,
  "ai-assistant": 529,
  "303": 854,
  "tb3po": 833,
  "breakbeat": 808,
  "po32-drum": 106,
  "signal": 503,
  "krautdrums": 516,
  "forge": 528,
  "davebox": 611,
  "chorddex": 548,
  "mrsample": 461,
  "dronage-tool": 413,
  "chordism": 251,
  "juno_control": 144,
  "helm": 219
}
