{
  "dexed": 2705,
  "sf2": 2625,
  "sfz": 2223,
  "m8": 2461,
  "minijv": 2839,
  "obxd": 2584,
  "cloudseed": 2181,
  "ottx": 393,
  "midiverb": 941,
  "tapescam": 2150,
  "psxverb": 1881,
  "mverb": 730,
  "tapedelay": 2852,
  "junologue-chorus": 1929,
  "sidcontrol": 1698,
  "braids": 2091,
  "hera": 1947,
  "surge": 2224,
  "moog": 2264,
  "webstream": 3094,
  "nam": 2094,
  "ducker": 2047,
  "pushnpull": 194,
  "radiogarden": 2238,
  "airplay": 2738,
  "streamrtsp": 1297,
  "clap": 2161,
  "gate": 2277,
  "control": 2704,
  "chiptune": 2236,
  "keydetect": 2188,
  "vocoder": 1829,
  "osirus": 2896,
  "superarp": 2131,
  "eucalypso": 1881,
  "granny": 2396,
  "freak": 1638,
  "mrdrums": 2011,
  "rex": 2274,
  "hush1": 2149,
  "nusaw": 1817,
  "usefulity": 1930,
  "samplerobot": 1526,
  "waveform-editor": 2750,
  "stretch": 2086,
  "stems": 1936,
  "plaits": 1960,
  "granular": 2077,
  "superboom": 1650,
  "performance-fx": 1657,
  "dj": 1490,
  "slicer": 1374,
  "verglas": 1443,
  "guitar-tuner": 815,
  "tuner": 1371,
  "dragonfly-hall": 1481,
  "punchfx": 1663,
  "structor": 1652,
  "weird-dreams": 2032,
  "dissolver": 2649,
  "spectra": 1871,
  "essaim": 1690,
  "chowtape": 1469,
  "ambiotica": 1064,
  "filter": 525,
  "wurl": 1606,
  "denis": 1579,
  "genera": 1659,
  "euclidrum": 2757,
  "branchage": 1420,
  "twinsampler": 1543,
  "impressive-chords": 1316,
  "midi-player": 811,
  "ai-manual": 779,
  "ai-assistant": 794,
  "303": 1192,
  "tb3po": 1314,
  "breakbeat": 1215,
  "po32-drum": 588,
  "signal": 791,
  "krautdrums": 819,
  "forge": 847,
  "davebox": 1141,
  "chorddex": 978,
  "mrsample": 749,
  "dronage-tool": 874,
  "chordism": 659,
  "juno_control": 465,
  "helm": 763,
  "fork": 325,
  "aphex": 296,
  "war_bells": 311,
  "movy": 132,
  "magneto": 17,
  "fizzik": 16,
  "palette": 16
}
