{
  "dexed": 2169,
  "sf2": 2229,
  "sfz": 1690,
  "m8": 2082,
  "minijv": 2198,
  "obxd": 1794,
  "cloudseed": 1748,
  "midiverb": 519,
  "tapescam": 1711,
  "psxverb": 1482,
  "mverb": 268,
  "tapedelay": 2401,
  "junologue-chorus": 1513,
  "sidcontrol": 1344,
  "braids": 1623,
  "hera": 1526,
  "surge": 1578,
  "moog": 1876,
  "webstream": 2312,
  "nam": 1463,
  "ducker": 1615,
  "radiogarden": 1779,
  "airplay": 2277,
  "streamrtsp": 936,
  "clap": 1619,
  "gate": 1907,
  "control": 2060,
  "chiptune": 1808,
  "keydetect": 1799,
  "vocoder": 1438,
  "osirus": 2279,
  "superarp": 1703,
  "eucalypso": 1494,
  "granny": 1986,
  "freak": 1254,
  "mrdrums": 1479,
  "rex": 1895,
  "hush1": 1731,
  "nusaw": 1433,
  "usefulity": 1548,
  "samplerobot": 1136,
  "waveform-editor": 2292,
  "stretch": 1660,
  "stems": 1521,
  "plaits": 1511,
  "granular": 1658,
  "superboom": 1252,
  "performance-fx": 1238,
  "dj": 1119,
  "slicer": 973,
  "verglas": 1047,
  "guitar-tuner": 396,
  "tuner": 996,
  "dragonfly-hall": 1088,
  "punchfx": 1254,
  "structor": 1266,
  "weird-dreams": 1524,
  "dissolver": 1756,
  "spectra": 1405,
  "essaim": 1209,
  "chowtape": 1048,
  "ambiotica": 188,
  "wurl": 1095,
  "denis": 1098,
  "genera": 1151,
  "euclidrum": 1152,
  "branchage": 1031,
  "twinsampler": 837,
  "impressive-chords": 824,
  "midi-player": 295,
  "ai-manual": 375,
  "ai-assistant": 382,
  "303": 656,
  "tb3po": 673,
  "breakbeat": 548,
  "signal": 339,
  "krautdrums": 347,
  "forge": 358,
  "davebox": 356,
  "chorddex": 261,
  "mrsample": 298
}
