{
  "dexed": 1296,
  "sf2": 1733,
  "sfz": 891,
  "m8": 1589,
  "minijv": 1521,
  "obxd": 1061,
  "cloudseed": 1178,
  "tapescam": 1164,
  "psxverb": 988,
  "tapedelay": 1847,
  "junologue-chorus": 994,
  "sidcontrol": 902,
  "braids": 1032,
  "hera": 1002,
  "surge": 1009,
  "moog": 1384,
  "webstream": 1614,
  "nam": 988,
  "ducker": 1078,
  "radiogarden": 1224,
  "airplay": 1494,
  "streamrtsp": 463,
  "clap": 947,
  "gate": 1441,
  "control": 1552,
  "chiptune": 1292,
  "keydetect": 1317,
  "vocoder": 956,
  "osirus": 1637,
  "superarp": 1183,
  "eucalypso": 1010,
  "granny": 1416,
  "freak": 692,
  "mrdrums": 950,
  "rex": 1340,
  "hush1": 1215,
  "nusaw": 946,
  "usefulity": 1069,
  "samplerobot": 638,
  "waveform-editor": 1538,
  "stretch": 1114,
  "stems": 959,
  "plaits": 875,
  "granular": 1074,
  "superboom": 752,
  "performance-fx": 706,
  "dj": 650,
  "slicer": 430,
  "verglas": 539,
  "tuner": 533,
  "dragonfly-hall": 588,
  "punchfx": 702,
  "structor": 734,
  "weird-dreams": 832,
  "dissolver": 648,
  "spectra": 723,
  "essaim": 529,
  "chowtape": 476,
  "wurl": 418,
  "denis": 418,
  "genera": 398,
  "euclidrum": 8,
  "branchage": 421
}
