{
  "dexed": 1533,
  "sf2": 1858,
  "sfz": 1032,
  "m8": 1711,
  "minijv": 1689,
  "obxd": 1189,
  "cloudseed": 1311,
  "tapescam": 1299,
  "psxverb": 1103,
  "tapedelay": 1973,
  "junologue-chorus": 1118,
  "sidcontrol": 1016,
  "braids": 1162,
  "hera": 1127,
  "surge": 1141,
  "moog": 1508,
  "webstream": 1782,
  "nam": 1110,
  "ducker": 1207,
  "radiogarden": 1347,
  "airplay": 1731,
  "streamrtsp": 576,
  "clap": 1066,
  "gate": 1558,
  "control": 1675,
  "chiptune": 1411,
  "keydetect": 1434,
  "vocoder": 1073,
  "osirus": 1790,
  "superarp": 1299,
  "eucalypso": 1123,
  "granny": 1551,
  "freak": 824,
  "mrdrums": 1080,
  "rex": 1482,
  "hush1": 1339,
  "nusaw": 1065,
  "usefulity": 1189,
  "samplerobot": 756,
  "waveform-editor": 1674,
  "stretch": 1249,
  "stems": 1093,
  "plaits": 1024,
  "granular": 1205,
  "superboom": 872,
  "performance-fx": 824,
  "dj": 758,
  "slicer": 554,
  "verglas": 657,
  "tuner": 645,
  "dragonfly-hall": 703,
  "punchfx": 829,
  "structor": 863,
  "weird-dreams": 967,
  "dissolver": 771,
  "spectra": 857,
  "essaim": 663,
  "chowtape": 603,
  "wurl": 545,
  "denis": 548,
  "genera": 565,
  "euclidrum": 195,
  "branchage": 568,
  "twinsampler": 226,
  "impressive-chords": 71
}
