{
  "dexed": 2417,
  "sf2": 2410,
  "sfz": 1944,
  "m8": 2255,
  "minijv": 2404,
  "obxd": 2051,
  "cloudseed": 1941,
  "midiverb": 709,
  "tapescam": 1921,
  "psxverb": 1673,
  "mverb": 474,
  "tapedelay": 2615,
  "junologue-chorus": 1712,
  "sidcontrol": 1510,
  "braids": 1836,
  "hera": 1721,
  "surge": 1794,
  "moog": 2053,
  "webstream": 2674,
  "nam": 1768,
  "ducker": 1806,
  "radiogarden": 1984,
  "airplay": 2490,
  "streamrtsp": 1100,
  "clap": 1863,
  "gate": 2076,
  "control": 2348,
  "chiptune": 2007,
  "keydetect": 1974,
  "vocoder": 1618,
  "osirus": 2488,
  "superarp": 1901,
  "eucalypso": 1672,
  "granny": 2169,
  "freak": 1431,
  "mrdrums": 1647,
  "rex": 2064,
  "hush1": 1925,
  "nusaw": 1609,
  "usefulity": 1724,
  "samplerobot": 1321,
  "waveform-editor": 2501,
  "stretch": 1850,
  "stems": 1711,
  "plaits": 1710,
  "granular": 1852,
  "superboom": 1434,
  "performance-fx": 1429,
  "dj": 1289,
  "slicer": 1154,
  "verglas": 1231,
  "guitar-tuner": 591,
  "tuner": 1173,
  "dragonfly-hall": 1262,
  "punchfx": 1430,
  "structor": 1439,
  "weird-dreams": 1753,
  "dissolver": 2245,
  "spectra": 1614,
  "essaim": 1431,
  "chowtape": 1235,
  "ambiotica": 527,
  "filter": 182,
  "wurl": 1325,
  "denis": 1321,
  "genera": 1386,
  "euclidrum": 1785,
  "branchage": 1206,
  "twinsampler": 1078,
  "impressive-chords": 1050,
  "midi-player": 491,
  "ai-manual": 554,
  "ai-assistant": 566,
  "303": 902,
  "tb3po": 876,
  "breakbeat": 865,
  "po32-drum": 160,
  "signal": 543,
  "krautdrums": 558,
  "forge": 570,
  "davebox": 662,
  "chorddex": 600,
  "mrsample": 497,
  "dronage-tool": 471,
  "chordism": 307,
  "juno_control": 186,
  "helm": 276
}
