{
  "dexed": 2228,
  "sf2": 2277,
  "sfz": 1745,
  "m8": 2125,
  "minijv": 2252,
  "obxd": 1857,
  "cloudseed": 1798,
  "midiverb": 570,
  "tapescam": 1765,
  "psxverb": 1529,
  "mverb": 318,
  "tapedelay": 2456,
  "junologue-chorus": 1567,
  "sidcontrol": 1385,
  "braids": 1675,
  "hera": 1576,
  "surge": 1629,
  "moog": 1920,
  "webstream": 2362,
  "nam": 1509,
  "ducker": 1663,
  "radiogarden": 1827,
  "airplay": 2330,
  "streamrtsp": 978,
  "clap": 1672,
  "gate": 1950,
  "control": 2104,
  "chiptune": 1858,
  "keydetect": 1846,
  "vocoder": 1484,
  "osirus": 2333,
  "superarp": 1757,
  "eucalypso": 1539,
  "granny": 2036,
  "freak": 1299,
  "mrdrums": 1525,
  "rex": 1936,
  "hush1": 1778,
  "nusaw": 1478,
  "usefulity": 1590,
  "samplerobot": 1182,
  "waveform-editor": 2340,
  "stretch": 1706,
  "stems": 1569,
  "plaits": 1564,
  "granular": 1708,
  "superboom": 1300,
  "performance-fx": 1287,
  "dj": 1163,
  "slicer": 1024,
  "verglas": 1092,
  "guitar-tuner": 443,
  "tuner": 1039,
  "dragonfly-hall": 1134,
  "punchfx": 1303,
  "structor": 1311,
  "weird-dreams": 1578,
  "dissolver": 1872,
  "spectra": 1455,
  "essaim": 1259,
  "chowtape": 1101,
  "ambiotica": 279,
  "wurl": 1150,
  "denis": 1148,
  "genera": 1204,
  "euclidrum": 1272,
  "branchage": 1076,
  "twinsampler": 883,
  "impressive-chords": 881,
  "midi-player": 342,
  "ai-manual": 418,
  "ai-assistant": 427,
  "303": 724,
  "tb3po": 722,
  "breakbeat": 598,
  "signal": 388,
  "krautdrums": 400,
  "forge": 407,
  "davebox": 408,
  "chorddex": 337,
  "mrsample": 345,
  "dronage-tool": 91
}
